testsuite/__init__.py
testsuite/_version.py
testsuite/asyncio_socket.py
testsuite/logcapture.py
testsuite/matching.py
testsuite/pytest_plugin.py
testsuite/tracing.py
testsuite/types.py
testsuite/_internal/__init__.py
testsuite/_internal/compare_transform.py
testsuite/_internal/fixture_class.py
testsuite/_internal/fixture_types.py
testsuite/_internal/logreader.py
testsuite/daemons/__init__.py
testsuite/daemons/pytest_plugin.py
testsuite/daemons/service_client.py
testsuite/daemons/service_daemon.py
testsuite/daemons/spawn.py
testsuite/databases/__init__.py
testsuite/databases/clickhouse/__init__.py
testsuite/databases/clickhouse/classes.py
testsuite/databases/clickhouse/control.py
testsuite/databases/clickhouse/discover.py
testsuite/databases/clickhouse/pytest_plugin.py
testsuite/databases/clickhouse/service.py
testsuite/databases/clickhouse/utils.py
testsuite/databases/clickhouse/scripts/find-clickhouse.sh
testsuite/databases/clickhouse/scripts/service-clickhouse
testsuite/databases/kafka/__init__.py
testsuite/databases/kafka/classes.py
testsuite/databases/kafka/pytest_plugin.py
testsuite/databases/kafka/service.py
testsuite/databases/kafka/scripts/find-kafka.sh
testsuite/databases/kafka/scripts/service-kafka
testsuite/databases/mongo/__init__.py
testsuite/databases/mongo/connection.py
testsuite/databases/mongo/ensure_db_indexes.py
testsuite/databases/mongo/mongo_schema.py
testsuite/databases/mongo/pytest_plugin.py
testsuite/databases/mongo/service.py
testsuite/databases/mongo/scripts/service-mongo
testsuite/databases/mysql/__init__.py
testsuite/databases/mysql/classes.py
testsuite/databases/mysql/control.py
testsuite/databases/mysql/discover.py
testsuite/databases/mysql/exceptions.py
testsuite/databases/mysql/pytest_plugin.py
testsuite/databases/mysql/service.py
testsuite/databases/mysql/utils.py
testsuite/databases/mysql/scripts/mysql-helper
testsuite/databases/mysql/scripts/service-mysql
testsuite/databases/pgsql/__init__.py
yandex_taxi_testsuite-0.4.1.dist-info/licenses/AUTHORS
yandex_taxi_testsuite-0.4.1.dist-info/licenses/LICENSE
yandex_taxi_testsuite-0.4.1.dist-info/METADATA
yandex_taxi_testsuite-0.4.1.dist-info/WHEEL
yandex_taxi_testsuite-0.4.1.dist-info/top_level.txt
yandex_taxi_testsuite-0.4.1.dist-info/RECORD
