Metadata-Version: 2.4
Name: yandex-taxi-testsuite
Version: 0.4.1
Summary: Yandex.Taxi Testsuite Package
Home-page: https://github.com/yandex/yandex-taxi-testsuite
License: MIT
Project-URL: Bug Tracker, https://github.com/yandex/yandex-taxi-testsuite/issues
Classifier: Programming Language :: Python :: 3
Classifier: License :: OSI Approved :: MIT License
Classifier: Operating System :: POSIX
Requires-Python: >=3.10
License-File: LICENSE
License-File: AUTHORS
Requires-Dist: packaging
Requires-Dist: PyYAML>=3.13
Requires-Dist: aiohttp>=3.5.4
Requires-Dist: yarl!=1.6,>=1.4.2
Requires-Dist: py>=1.10
Requires-Dist: pytest-aiohttp>=0.3.0
Requires-Dist: pytest-asyncio!=0.22.*,!=0.23.*,!=0.24.*
Requires-Dist: pytest>=4.5.0
Requires-Dist: python-dateutil>=2.7.3
Requires-Dist: cached-property>=1.5.1
Provides-Extra: mongodb
Requires-Dist: pymongo>=3.7.1; extra == "mongodb"
Provides-Extra: postgresql
Requires-Dist: psycopg2>=2.7.5; extra == "postgresql"
Requires-Dist: yandex-pgmigrate; extra == "postgresql"
Provides-Extra: postgresql-binary
Requires-Dist: psycopg2-binary>=2.7.5; extra == "postgresql-binary"
Provides-Extra: clickhouse
Requires-Dist: clickhouse-driver>=0.2.0; extra == "clickhouse"
Provides-Extra: redis
Requires-Dist: python-redis>=0.2.1; extra == "redis"
Requires-Dist: redis>=2.10.6; extra == "redis"
Provides-Extra: mysql
Requires-Dist: PyMySQL>=0.9.2; extra == "mysql"
Provides-Extra: rabbitmq
Requires-Dist: aio-pika>=8.1.0; extra == "rabbitmq"
Provides-Extra: kafka
Requires-Dist: aiokafka>=0.9.0; extra == "kafka"
Dynamic: license-file
Dynamic: provides-extra
Dynamic: requires-dist
